setup.py
Catemcli/Catemcli.py
Catemcli/logger.py
Catemcli/storage.py
Catemcli.egg-info/PKG-INFO
Catemcli.egg-info/SOURCES.txt
Catemcli.egg-info/dependency_links.txt
Catemcli.egg-info/entry_points.txt
Catemcli.egg-info/requires.txt
Catemcli.egg-info/top_level.txt