Metadata-Version: 1.0
Name: Catemcli
Version: 0.1
Summary: A email client in terminal
Home-page: https://github.com/greycatya
Author: Graycatya
Author-email: greycatya@163.com
License: UNKNOWN
Platform: UNKNOWN
